aznt/__init__.py
aznt/azntnumbers.py
aznt/azntplots.py
aznt/azntprimality.py
aznt-0.0.44.dist-info/LICENCE.txt
aznt-0.0.44.dist-info/METADATA
aznt-0.0.44.dist-info/WHEEL
aznt-0.0.44.dist-info/top_level.txt
aznt-0.0.44.dist-info/RECORD
