Metadata-Version: 2.1
Name: aznt
Version: 0.0.44
Summary: From A to Z Number Theory
Author-email: "Adrian Zapała, MSc" <adrian.zapala@outlook.com>
Keywords: aznt,numbers,number theory,primes,prime numbers,math
Classifier: Development Status :: 4 - Beta
Classifier: Intended Audience :: Education
Classifier: Intended Audience :: End Users/Desktop
Classifier: Intended Audience :: Information Technology
Classifier: Intended Audience :: Science/Research
Classifier: License :: OSI Approved :: MIT License
Classifier: Operating System :: OS Independent
Classifier: Programming Language :: Python :: 3.11
Classifier: Topic :: Scientific/Engineering :: Artificial Intelligence
Classifier: Topic :: Scientific/Engineering
Classifier: Topic :: Scientific/Engineering :: Information Analysis
Classifier: Topic :: Scientific/Engineering :: Mathematics
Classifier: Topic :: Security :: Cryptography
Classifier: Topic :: Software Development :: Libraries :: Python Modules
Requires-Python: >=3.11
License-File: LICENCE.txt
Requires-Dist: mpmath
Requires-Dist: matplotlib
Requires-Dist: numpy
